[
  {
    "id": 38195,
    "title": "Fire’s Footprint on Santa Rosa Island",
    "authors": [
      {
        "name": "NASA",
        "socials": null
      }
    ],
    "url": "https://science.nasa.gov/earth/earth-observatory/fires-footprint-on-santa-rosa-island/",
    "image_url": "https://assets.science.nasa.gov/dynamicimage/assets/science/esd/eo/images/iotd/2026/fire%E2%80%99s-footprint-on-santa-rosa-island/channelislandsfire653_oli2_20260516.jpg",
    "news_site": "NASA",
    "summary": "A wildland fire charred grassland, coastal sage scrub, and chaparral across one-third of the island, the second largest of the Channel Islands.",
    "published_at": "2026-06-02T04:01:00Z",
    "updated_at": "2026-06-02T04:10:08.970796Z",
    "featured": false,
    "launches": [],
    "events": [],
    "detailed_news": ""
  },
  {
    "id": 38194,
    "title": "France to fly two astronauts on Vast missions",
    "authors": [
      {
        "name": "Jeff Foust",
        "socials": {
          "x": "https://x.com/jeff_foust",
          "youtube": "",
          "instagram": "",
          "linkedin": "https://www.linkedin.com/in/jefffoust",
          "mastodon": "https://mastodon.social/@jfoust",
          "bluesky": "https://bsky.app/profile/jfoust.bsky.social"
        }
      }
    ],
    "url": "https://spacenews.com/france-to-fly-two-astronauts-on-vast-missions/",
    "image_url": "https://i0.wp.com/spacenews.com/wp-content/uploads/2026/06/vast-france.jpeg?fit=1024%2C576&ssl=1",
    "news_site": "SpaceNews",
    "summary": "\nCommercial space station developer Vast has reached an agreement with the French government to fly two French astronauts on its missions, including the first flight to its Haven-1 space station.\nThe post France to fly two astronauts on Vast missions appeared first on SpaceNews.",
    "published_at": "2026-06-02T01:05:03Z",
    "updated_at": "2026-06-02T01:10:19.881000Z",
    "featured": false,
    "launches": [],
    "events": [],
    "detailed_news": ""
  },
  {
    "id": 38193,
    "title": "NASA Agrees with Industry, Keep CLD Program As Is",
    "authors": [
      {
        "name": "Marcia Smith",
        "socials": null
      }
    ],
    "url": "https://spacepolicyonline.com/news/nasa-agrees-with-industry-keep-cld-program-as-is/",
    "image_url": "https://spacepolicyonline.com/wp-content/uploads/2025/03/Crew-10-view-of-ISS-Mar-15-25-300x160.png",
    "news_site": "SpacePolicyOnline.com",
    "summary": "NASA is backing off its March announcement proposing a significant change to ensuring that at least one commercial space station is ready to replace the International Space Station (ISS) at […]",
    "published_at": "2026-06-02T00:45:29Z",
    "updated_at": "2026-06-02T00:50:15.859638Z",
    "featured": false,
    "launches": [],
    "events": [],
    "detailed_news": ""
  },
  {
    "id": 38192,
    "title": "NASA Awards Modification Contract for Reduced Gravity Test Aircraft",
    "authors": [
      {
        "name": "NASA",
        "socials": null
      }
    ],
    "url": "https://www.nasa.gov/news-release/nasa-awards-modification-contract-for-reduced-gravity-test-aircraft/",
    "image_url": "https://www.nasa.gov/wp-content/uploads/2026/04/nasa-meatball-1.webp",
    "news_site": "NASA",
    "summary": "NASA selected Denmar Technical Services of Nevada to provide aircraft modifications, maintenance, and testing services to the Human Spaceflight Mission Directorate at NASA’s Armstrong Flight Research Center in Edwards, California, and Johnson Space Center in Houston. The award is a firm-fixed-price contract and will be time and material for any over and above and unforeseen […]",
    "published_at": "2026-06-01T23:45:59Z",
    "updated_at": "2026-06-01T23:50:05.502312Z",
    "featured": false,
    "launches": [],
    "events": [],
    "detailed_news": ""
  },
  {
    "id": 38191,
    "title": "Launch Preview: SpaceX and Chinese rockets to launch internet satellites to LEO",
    "authors": [
      {
        "name": "Haygen Warren",
        "socials": null
      }
    ],
    "url": "https://www.nasaspaceflight.com/2026/06/launch-preview-060126/",
    "image_url": "https://www.nasaspaceflight.com/wp-content/uploads/2025/05/julia-streak-3.jpg",
    "news_site": "NASASpaceflight",
    "summary": "SpaceX and Chinese launches dominate this week’s launch manifest, which features six missions from five…\nThe post Launch Preview: SpaceX and Chinese rockets to launch internet satellites to LEO appeared first on NASASpaceFlight.com.",
    "published_at": "2026-06-01T22:05:08Z",
    "updated_at": "2026-06-01T22:10:16.258700Z",
    "featured": false,
    "launches": [],
    "events": [],
    "detailed_news": "SpaceX and Chinese launches dominate this week’s launch manifest, which features six missions from five…\nThe post Launch Preview: SpaceX and Chinese rockets to launch internet satellites to LEO appeared first on NASASpaceFlight.com."
  },
  {
    "id": 38190,
    "title": "NASA Invites Media to See Roman Space Telescope Arrive at Kennedy",
    "authors": [
      {
        "name": "NASA",
        "socials": null
      }
    ],
    "url": "https://www.nasa.gov/news-release/nasa-invites-media-to-see-roman-space-telescope-arrive-at-kennedy/",
    "image_url": "https://www.nasa.gov/wp-content/uploads/2026/04/roman-option-3.jpg",
    "news_site": "NASA",
    "summary": "Registration is open for media to cover the arrival of NASA’s Nancy Grace Roman Space Telescope at the agency’s Kennedy Space Center in Florida in the coming weeks. The observatory will arrive aboard NASA’s Pegasus barge from NASA’s Goddard Space Flight Center in Greenbelt, Maryland, where teams completed its construction, assembly, and testing. Credentialed media […]",
    "published_at": "2026-06-01T21:22:52Z",
    "updated_at": "2026-06-01T21:30:06.909581Z",
    "featured": false,
    "launches": [],
    "events": [],
    "detailed_news": ""
  },
  {
    "id": 38189,
    "title": "PLD Space Triples Investment in Launch Facility to €35 Million",
    "authors": [
      {
        "name": "European Spaceflight",
        "socials": null
      }
    ],
    "url": "https://europeanspaceflight.com/pld-space-triples-investment-in-launch-facility-to-e35-million/",
    "image_url": "https://europeanspaceflight.com/wp-content/uploads/2026/06/PLD-Space-Triples-Investment-in-Launch-Facility-to-E35-Million.webp",
    "news_site": "European Spaceflight",
    "summary": "PLD Space has announced that it will invest €35 million in the development of its launch facility at the Guiana Space Centre in French Guiana, more than triple the amount the company initially planned. In June 2024, PLD Space announced that it planned to “make a very efficient 10 million euros investment for the construction […]\nThe post PLD Space Triples Investment in Launch Facility to €35 Million appeared first on European Spaceflight.",
    "published_at": "2026-06-01T19:06:32Z",
    "updated_at": "2026-06-01T19:10:16.356673Z",
    "featured": false,
    "launches": [],
    "events": [],
    "detailed_news": ""
  },
  {
    "id": 38187,
    "title": "NASA to Conduct Low-Altitude Flights Near Houston",
    "authors": [
      {
        "name": "NASA",
        "socials": null
      }
    ],
    "url": "https://www.nasa.gov/general/nasa-to-conduct-low-altitude-flights-near-houston/",
    "image_url": "https://www.nasa.gov/wp-content/uploads/2026/06/ed07-0027-56large.jpg",
    "news_site": "NASA",
    "summary": "Five research aircraft will support a Student Airborne Research Program (SARP) mission out of Ellington Field in Houston. Flights are expected from Wednesday, June 3 to Saturday, June 13. During the mission, select maneuvers will be conducted at low altitudes over the Houston area.  Pilots will fly remote sensing payloads in raster patterns, or parallel back-and-forth lines. The instruments flown could help […]",
    "published_at": "2026-06-01T18:29:50Z",
    "updated_at": "2026-06-01T18:30:12.058054Z",
    "featured": false,
    "launches": [],
    "events": [],
    "detailed_news": ""
  },
  {
    "id": 38188,
    "title": "What’s Up: June 2026 Skywatching Tips from NASA",
    "authors": [
      {
        "name": "NASA",
        "socials": null
      }
    ],
    "url": "https://science.nasa.gov/solar-system/whats-up-june-2026-skywatching-tips-from-nasa/",
    "image_url": "https://assets.science.nasa.gov/dynamicimage/assets/science/psd/solar-system/skywatching/2026/june/june9.png",
    "news_site": "NASA",
    "summary": "Venus and Jupiter meet after sunset, the Moon passes in front of Venus, summer begins, and deep-sky treasures rise into view.",
    "published_at": "2026-06-01T18:13:46Z",
    "updated_at": "2026-06-01T19:10:10.112893Z",
    "featured": false,
    "launches": [],
    "events": [],
    "detailed_news": ""
  },
  {
    "id": 38186,
    "title": "Op-Ed: Misuse of Commercial Programs Sets NASA Up for Failure",
    "authors": [
      {
        "name": "Emily B",
        "socials": null
      }
    ],
    "url": "https://www.spacescout.info/2026/06/op-ed-misuse-of-commercial-programs-sets-nasa-up-for-failure/",
    "image_url": "https://i0.wp.com/www.spacescout.info/wp-content/uploads/2026/05/commercial_overuse_banner-1.png",
    "news_site": "Space Scout",
    "summary": "Despite Starliner being perhaps the most visible example of a commercial program gone wrong, it is far from unique in its problems.",
    "published_at": "2026-06-01T15:42:10Z",
    "updated_at": "2026-06-01T15:50:30.208106Z",
    "featured": false,
    "launches": [],
    "events": [],
    "detailed_news": ""
  },
  {
    "id": 38184,
    "title": "Flight Log—About Pilots",
    "authors": [
      {
        "name": "NASA",
        "socials": null
      }
    ],
    "url": "https://www.nasa.gov/aeronautics/aeronautics-stem/flight-log-about-pilots/",
    "image_url": "https://www.nasa.gov/wp-content/uploads/2025/10/first-pilot-id-web.png",
    "news_site": "NASA",
    "summary": "Introduction From the first glider flight to the first powered flight, aviation pioneers have paved the way for remarkable innovations in flight. At NASA, our pilots conduct research, study wildfires, and support unmanned aircraft missions. In fact, out of the 360 astronauts who have been selected, 191 of them have been pilots!   The History of Pilot Certificates […]",
    "published_at": "2026-06-01T15:39:35Z",
    "updated_at": "2026-06-01T15:40:10.246258Z",
    "featured": false,
    "launches": [],
    "events": [],
    "detailed_news": ""
  },
  {
    "id": 38185,
    "title": "Pilot Flight Logs",
    "authors": [
      {
        "name": "NASA",
        "socials": null
      }
    ],
    "url": "https://www.nasa.gov/aeronautics/aeronautics-stem/pilot-flight-logs/",
    "image_url": "https://www.nasa.gov/wp-content/uploads/2025/10/wright-brother-flight-notebook.jpg",
    "news_site": "NASA",
    "summary": "Pilot Flight Logs Pilot flight logs, which have been around in one form or another since the beginning of flight, have served several purposes. Today, pilot logbooks are used by aviators to provide a record of their flights, including current and accumulated flight time, number and locations of takeoffs and landings, as well as unique […]",
    "published_at": "2026-06-01T15:38:43Z",
    "updated_at": "2026-06-01T15:40:10.321947Z",
    "featured": false,
    "launches": [],
    "events": [],
    "detailed_news": ""
  },
  {
    "id": 38183,
    "title": "Webb sniffs methane from interstellar Comet 3I/ATLAS",
    "authors": [
      {
        "name": "ESA",
        "socials": null
      }
    ],
    "url": "https://www.esa.int/ESA_Multimedia/Images/2026/06/Webb_sniffs_methane_from_interstellar_Comet_3I_ATLAS",
    "image_url": "https://www.esa.int/var/esa/storage/images/esa_multimedia/images/2026/06/webb_sniffs_methane_from_interstellar_comet_3i_atlas/27299787-6-eng-GB/Webb_sniffs_methane_from_interstellar_Comet_3I_ATLAS_card_full.png",
    "news_site": "ESA",
    "summary": "From the ESA Blogs.",
    "published_at": "2026-06-01T15:00:00Z",
    "updated_at": "2026-06-01T15:10:19.978317Z",
    "featured": false,
    "launches": [],
    "events": [],
    "detailed_news": ""
  },
  {
    "id": 38182,
    "title": "Northrop Grumman partners with Apex on space-based interceptors for Golden Dome",
    "authors": [
      {
        "name": "Sandra Erwin",
        "socials": null
      }
    ],
    "url": "https://spacenews.com/northrop-grumman-partners-with-apex-on-space-based-interceptors-for-golden-dome/",
    "image_url": "https://i0.wp.com/spacenews.com/wp-content/uploads/2026/06/Northrop-Grumman-to-Demonstrate-Space-Based-Interceptor-Capabilities-with-Apex-for-US-Space-Force-scaled.png?fit=1024%2C576&ssl=1",
    "news_site": "SpaceNews",
    "summary": "\nThe Los Angeles-based startup manufactures standardized satellite buses designed to be produced more quickly and at lower cost than traditional government spacecraft\nThe post Northrop Grumman partners with Apex on space-based interceptors for Golden Dome appeared first on SpaceNews.",
    "published_at": "2026-06-01T14:57:04Z",
    "updated_at": "2026-06-01T15:00:41.300749Z",
    "featured": false,
    "launches": [],
    "events": [],
    "detailed_news": ""
  },
  {
    "id": 38180,
    "title": "Pretty in Pink",
    "authors": [
      {
        "name": "NASA",
        "socials": null
      }
    ],
    "url": "https://www.nasa.gov/image-article/pretty-in-pink-2/",
    "image_url": "https://www.nasa.gov/wp-content/uploads/2026/05/55270825152-a1118117db-o.jpg",
    "news_site": "NASA",
    "summary": "This image of Westerlund 2 released on March 19, 2026, features Chandra X-ray Observatory data (pink) and infrared data from NASA’S James Webb Space Telescope (red, orange, green, cyan, and blue). Scores of gleaming stars ringed in neon pink stretch across the frame, highlighting a cluster where stars are between one and three million years […]",
    "published_at": "2026-06-01T14:30:17Z",
    "updated_at": "2026-06-01T14:43:20.634720Z",
    "featured": false,
    "launches": [
      {
        "launch_id": "0a5d89b0-aa14-4140-b72d-fbcc8340b222",
        "provider": "Launch Library 2"
      }
    ],
    "events": [],
    "detailed_news": ""
  },
  {
    "id": 38181,
    "title": "Smile: cleanroom to space",
    "authors": [
      {
        "name": "ESA",
        "socials": null
      }
    ],
    "url": "https://www.esa.int/ESA_Multimedia/Videos/2026/06/Smile_cleanroom_to_space",
    "image_url": "https://www.esa.int/var/esa/storage/images/esa_multimedia/videos/2026/06/smile_cleanroom_to_space/27303296-1-eng-GB/Smile_cleanroom_to_space_card_full.png",
    "news_site": "ESA",
    "summary": "Smile successfully launched from Europe’s Spaceport in French Guiana on 19 May 2026.",
    "published_at": "2026-06-01T14:00:00Z",
    "updated_at": "2026-06-01T14:51:30.702441Z",
    "featured": false,
    "launches": [
      {
        "launch_id": "b31313da-ee5d-42b2-9a27-20cc18105276",
        "provider": "Launch Library 2"
      }
    ],
    "events": [],
    "detailed_news": ""
  },
  {
    "id": 38179,
    "title": "Spaceport facility bonds are now law – and they fundamentally change space infrastructure finance",
    "authors": [
      {
        "name": "Craig Hrinkevich",
        "socials": null
      }
    ],
    "url": "https://spacenews.com/spaceport-facility-bonds-are-now-law-and-they-fundamentally-change-space-infrastructure-finance/",
    "image_url": "https://i0.wp.com/spacenews.com/wp-content/uploads/2026/02/f9-20260207.jpeg?fit=1024%2C541&ssl=1",
    "news_site": "SpaceNews",
    "summary": "\nAfter more than three decades in public and project finance, I have learned that real inflection points in infrastructure development rarely announce themselves loudly. They usually arrive embedded in financing […]\nThe post Spaceport facility bonds are now law – and they fundamentally change space infrastructure finance appeared first on SpaceNews.",
    "published_at": "2026-06-01T13:00:00Z",
    "updated_at": "2026-06-01T13:10:27.583554Z",
    "featured": false,
    "launches": [],
    "events": [],
    "detailed_news": ""
  },
  {
    "id": 38177,
    "title": "China conducts surprise launch of Long March 12B, delivers Qianfan satellites on debut flight",
    "authors": [
      {
        "name": "Andrew Jones",
        "socials": null
      }
    ],
    "url": "https://spacenews.com/china-conducts-surprise-launch-of-long-march-12b-delivers-qianfan-satellites-on-debut-flight/",
    "image_url": "https://i0.wp.com/spacenews.com/wp-content/uploads/2026/06/CZ12B-debut-qianfan-sats-JSLC-1june2026-OS1.jpg?fit=1024%2C680&ssl=1",
    "news_site": "SpaceNews",
    "summary": "China conducted the maiden launch of its reusable Long March 12B rocket Monday, providing no advance warning and delivering operational payloads to orbit.\r\nThe post China conducts surprise launch of Long March 12B, delivers Qianfan satellites on debut flight appeared first on SpaceNews.",
    "published_at": "2026-06-01T10:43:39Z",
    "updated_at": "2026-06-01T11:12:42.906335Z",
    "featured": false,
    "launches": [
      {
        "launch_id": "459225a2-dc1a-43d7-8c2c-78f9552b0a05",
        "provider": "Launch Library 2"
      }
    ],
    "events": [],
    "detailed_news": ""
  },
  {
    "id": 38176,
    "title": "Space science for your heart",
    "authors": [
      {
        "name": "ESA",
        "socials": null
      }
    ],
    "url": "https://www.esa.int/ESA_Multimedia/Images/2026/06/Space_science_for_your_heart",
    "image_url": "https://www.esa.int/var/esa/storage/images/esa_multimedia/images/2026/06/space_science_for_your_heart/27303239-1-eng-GB/Space_science_for_your_heart_card_full.jpg",
    "news_site": "ESA",
    "summary": "From the ESA Blogs.",
    "published_at": "2026-06-01T10:18:00Z",
    "updated_at": "2026-06-01T10:30:18.289793Z",
    "featured": false,
    "launches": [],
    "events": [],
    "detailed_news": ""
  },
  {
    "id": 38175,
    "title": "New Glenn failure worsens constrained launch market",
    "authors": [
      {
        "name": "Jeff Foust",
        "socials": {
          "x": "https://x.com/jeff_foust",
          "youtube": "",
          "instagram": "",
          "linkedin": "https://www.linkedin.com/in/jefffoust",
          "mastodon": "https://mastodon.social/@jfoust",
          "bluesky": "https://bsky.app/profile/jfoust.bsky.social"
        }
      }
    ],
    "url": "https://spacenews.com/new-glenn-failure-worsens-constrained-launch-market/",
    "image_url": "https://i0.wp.com/spacenews.com/wp-content/uploads/2026/06/isaacman-lc36.jpeg?fit=1024%2C683&ssl=1",
    "news_site": "SpaceNews",
    "summary": "The explosion of a New Glenn rocket has generated reverberations across the space industry with the rocket out of service for potentially a year or more.\r\nThe post New Glenn failure worsens constrained launch market appeared first on SpaceNews.",
    "published_at": "2026-06-01T09:46:33Z",
    "updated_at": "2026-06-01T09:55:08.735266Z",
    "featured": false,
    "launches": [
      {
        "launch_id": "ca3d56b7-2175-48e4-9a6a-2ecc9996d96b",
        "provider": "Launch Library 2"
      }
    ],
    "events": [],
    "detailed_news": ""
  },
  {
    "id": 38174,
    "title": "China launches test direct-to-device satellites for multiple projects",
    "authors": [
      {
        "name": "Andrew Jones",
        "socials": null
      }
    ],
    "url": "https://spacenews.com/china-launches-test-direct-to-device-satellites-for-multiple-projects/",
    "image_url": "https://i0.wp.com/spacenews.com/wp-content/uploads/2026/06/CZ2D-4satellite-internet-test-satellites-XSLC-30may2026-OS-1.jpg?fit=1024%2C682&ssl=1",
    "news_site": "SpaceNews",
    "summary": "China capped a busy month of launches by sending four new satellite internet test satellites into orbit with a workhorse hypergolic rocket.\r\nThe post China launches test direct-to-device satellites for multiple projects appeared first on SpaceNews.",
    "published_at": "2026-06-01T09:37:01Z",
    "updated_at": "2026-06-01T09:41:42.175920Z",
    "featured": false,
    "launches": [
      {
        "launch_id": "0ab3587d-bb8c-4515-a321-2ec154840659",
        "provider": "Launch Library 2"
      }
    ],
    "events": [],
    "detailed_news": ""
  },
  {
    "id": 38178,
    "title": "Gravity Waves From Super Typhoon Sinlaku",
    "authors": [
      {
        "name": "NASA",
        "socials": null
      }
    ],
    "url": "https://science.nasa.gov/earth/earth-observatory/gravity-waves-from-super-typhoon-sinlaku/",
    "image_url": "https://assets.science.nasa.gov/dynamicimage/assets/science/esd/eo/images/iotd/2026/gravity-waves-from-super-typhoon-sinlaku/sinlaku_gravitywaves_vir_20260412.jpg",
    "news_site": "NASA",
    "summary": "Satellites observed striking upper-atmosphere phenomena generated by an intensifying tropical cyclone.",
    "published_at": "2026-06-01T04:01:00Z",
    "updated_at": "2026-06-01T13:10:08.781015Z",
    "featured": false,
    "launches": [],
    "events": [],
    "detailed_news": ""
  },
  {
    "id": 38173,
    "title": "Ancient black hole sheds new light on Webb’s Little Red Dots",
    "authors": [
      {
        "name": "Martijn Luinstra",
        "socials": null
      }
    ],
    "url": "https://www.nasaspaceflight.com/2026/05/webb-abell2744-qso1/",
    "image_url": "https://www.nasaspaceflight.com/wp-content/uploads/2026/05/cso1_lead.jpg",
    "news_site": "NASASpaceflight",
    "summary": "Using the joint NASA/European Space Agency/Canadian Space Agency James Webb Space Telescope, an international team…\nThe post Ancient black hole sheds new light on Webb’s Little Red Dots appeared first on NASASpaceFlight.com.",
    "published_at": "2026-05-31T23:36:19Z",
    "updated_at": "2026-05-31T23:40:11.455043Z",
    "featured": false,
    "launches": [],
    "events": [],
    "detailed_news": "Using the joint NASA/European Space Agency/Canadian Space Agency James Webb Space Telescope, an international team…\nThe post Ancient black hole sheds new light on Webb’s Little Red Dots appeared first on NASASpaceFlight.com."
  },
  {
    "id": 38172,
    "title": "What’s Happening in Space Policy May 31-June 6, 2026",
    "authors": [
      {
        "name": "Marcia Smith",
        "socials": null
      }
    ],
    "url": "https://spacepolicyonline.com/news/whats-happening-in-space-policy-may-31-june-6-2026/",
    "image_url": "https://spacepolicyonline.com/wp-content/uploads/2025/08/Crew-11-on-chairs-NASA-263x300.png",
    "news_site": "SpacePolicyOnline.com",
    "summary": "Here is SpacePolicyOnline.com’s list of space policy events for the week of May 31-June 6, 2026 and any insight we can offer about them. The Senate and House are in […]",
    "published_at": "2026-05-31T22:02:44Z",
    "updated_at": "2026-05-31T22:10:13.713801Z",
    "featured": false,
    "launches": [],
    "events": [],
    "detailed_news": ""
  },
  {
    "id": 38171,
    "title": "Italy Turns to Tall Ship to Simulate Stresses of Long-Duration Spaceflight",
    "authors": [
      {
        "name": "European Spaceflight",
        "socials": null
      }
    ],
    "url": "https://europeanspaceflight.com/italy-turns-to-tall-ship-to-simulate-stresses-of-long-duration-spaceflight/",
    "image_url": "https://europeanspaceflight.com/wp-content/uploads/2026/05/Italy-Turns-to-Tall-Ship-to-Simulate-Stresses-of-Long-Duration-Spaceflight.webp",
    "news_site": "European Spaceflight",
    "summary": "The Italian Space Agency (ASI) has enlisted students from the country’s Naval Academy aboard a tall ship to examine how the human body responds to the stresses of long-duration spaceflight as part of its ICE-Blue initiative. In 2024, ASI signed an Operational Agreement with the Italian Navy, under which the ICE-BLUE initiative was launched in […]\nThe post Italy Turns to Tall Ship to Simulate Stresses of Long-Duration Spaceflight appeared first on European Spaceflight.",
    "published_at": "2026-05-31T14:09:32Z",
    "updated_at": "2026-05-31T14:10:11.330182Z",
    "featured": false,
    "launches": [],
    "events": [],
    "detailed_news": ""
  },
  {
    "id": 38170,
    "title": "FAA documents outline SpaceX plans for Starfall reentry vehicles",
    "authors": [
      {
        "name": "Jeff Foust",
        "socials": {
          "x": "https://x.com/jeff_foust",
          "youtube": "",
          "instagram": "",
          "linkedin": "https://www.linkedin.com/in/jefffoust",
          "mastodon": "https://mastodon.social/@jfoust",
          "bluesky": "https://bsky.app/profile/jfoust.bsky.social"
        }
      }
    ],
    "url": "https://spacenews.com/faa-documents-outline-spacex-plans-for-starfall-reentry-vehicles/",
    "image_url": "https://i0.wp.com/spacenews.com/wp-content/uploads/2026/05/starfall.jpeg?fit=1024%2C544&ssl=1",
    "news_site": "SpaceNews",
    "summary": "\nFederal Aviation Administration documents have provided new details about a SpaceX project to develop and test reentry vehicles that could be used to support in-space manufacturing projects.\nThe post FAA documents outline SpaceX plans for Starfall reentry vehicles appeared first on SpaceNews.",
    "published_at": "2026-05-31T09:26:19Z",
    "updated_at": "2026-05-31T09:30:20.490638Z",
    "featured": false,
    "launches": [],
    "events": [],
    "detailed_news": ""
  },
  {
    "id": 38169,
    "title": "Blue Origin gets national security launch task order hours before New Glenn explosion",
    "authors": [
      {
        "name": "Sandra Erwin",
        "socials": null
      }
    ],
    "url": "https://spacenews.com/blue-origin-gets-national-security-launch-task-order-hours-before-new-glenn-explosion/",
    "image_url": "https://i0.wp.com/spacenews.com/wp-content/uploads/2026/05/HJhyho4XcAAKy5F.jpeg?fit=1024%2C683&ssl=1",
    "news_site": "SpaceNews",
    "summary": "\nU.S. Space Force, National Reconnaissance Office ‘remain committed partners with Blue Origin’\nThe post Blue Origin gets national security launch task order hours before New Glenn explosion appeared first on SpaceNews.",
    "published_at": "2026-05-30T21:06:37Z",
    "updated_at": "2026-05-30T21:10:18.714979Z",
    "featured": false,
    "launches": [],
    "events": [],
    "detailed_news": ""
  },
  {
    "id": 38168,
    "title": "Live coverage: SpaceX to launch 50th Starlink mission of 2026",
    "authors": [
      {
        "name": "Will Robinson-Smith",
        "socials": null
      }
    ],
    "url": "https://spaceflightnow.com/2026/05/30/live-coverage-spacex-to-launch-50th-starlink-mission-of-2026/",
    "image_url": "http://spaceflightnow.com/wp-content/uploads/2025/09/20250818_Starlink_G17_5_Vertical.jpg",
    "news_site": "Spaceflight Now",
    "summary": "The Starlink 17-41 mission is SpaceX’s 10th and final launch of May. Liftoff of the Falcon 9 rocket from pad 4E at Vandenberg Space Force Base is scheduled for 8:25 a.m. PDT (11:25 a.m. EDT / 1525 UTC). ",
    "published_at": "2026-05-30T13:46:18Z",
    "updated_at": "2026-05-30T13:50:17.306479Z",
    "featured": false,
    "launches": [],
    "events": [],
    "detailed_news": ""
  },
  {
    "id": 38167,
    "title": "Repercussions of New Glenn’s Explosion Still Coming Into Focus",
    "authors": [
      {
        "name": "Marcia Smith",
        "socials": null
      }
    ],
    "url": "https://spacepolicyonline.com/news/repercussions-of-new-glenns-explosion-still-coming-into-focus/",
    "image_url": "https://spacepolicyonline.com/wp-content/uploads/2026/05/faa-new-glenn-expl-300x39.jpg",
    "news_site": "SpacePolicyOnline.com",
    "summary": "The repercussions of last night’s explosion of Blue Origin’s New Glenn rocket during a pre-launch test will take some time to assess. Among the key questions are not only what […]",
    "published_at": "2026-05-29T22:21:19Z",
    "updated_at": "2026-05-29T22:30:14.991929Z",
    "featured": false,
    "launches": [],
    "events": [],
    "detailed_news": ""
  },
  {
    "id": 38166,
    "title": "Live coverage: ULA to launch 29 Amazon Leo satellites on Atlas 5 rocket from Cape Canaveral",
    "authors": [
      {
        "name": "Will Robinson-Smith",
        "socials": null
      }
    ],
    "url": "https://spaceflightnow.com/2026/05/29/live-coverage-ula-to-launch-29-amazon-leo-satellites-on-atlas-5-rocket-from-cape-canaveral-2/",
    "image_url": "http://spaceflightnow.com/wp-content/uploads/2026/05/20260529_LA-07_prelaunch_AB-1.jpeg",
    "news_site": "Spaceflight Now",
    "summary": "The Leo Atlas 07 mission is the second to last flight that Amazon booked on a United Launch Alliance Atlas 5 rocket. Liftoff from pad 41 at Cape Canaveral Space Force Station is scheduled during a window that opens at 7:33 p.m. EDT (2333 UTC). ",
    "published_at": "2026-05-29T21:52:15Z",
    "updated_at": "2026-05-29T22:00:25.455692Z",
    "featured": false,
    "launches": [],
    "events": [],
    "detailed_news": ""
  },
  {
    "id": 38165,
    "title": "NASA Awards Contract for Johnson Space Center Infrastructure",
    "authors": [
      {
        "name": "NASA",
        "socials": null
      }
    ],
    "url": "https://www.nasa.gov/news-release/nasa-awards-contract-for-johnson-space-center-infrastructure/",
    "image_url": "https://www.nasa.gov/wp-content/uploads/2026/04/nasa-meatball-1.webp",
    "news_site": "NASA",
    "summary": "NASA has selected seven companies to provide construction, revitalization, and infrastructure improvements at the agency’s Johnson Space Center in Houston. The Johnson Space Center Multiple Award Construction Contract supports up to $300 million in upgrades to mission‑support facilities, utilities, and equipment across the NASA Johnson campus. All funds must be obligated by Sept. 30, 2026. […]",
    "published_at": "2026-05-29T21:24:11Z",
    "updated_at": "2026-05-29T21:30:06.111884Z",
    "featured": false,
    "launches": [],
    "events": [],
    "detailed_news": ""
  },
  {
    "id": 38164,
    "title": "NASA Hosts SpaceX Crew-11 Astronauts for Public Event at Headquarters",
    "authors": [
      {
        "name": "NASA",
        "socials": null
      }
    ],
    "url": "https://www.nasa.gov/news-release/nasa-hosts-spacex-crew-11-astronauts-for-public-event-at-headquarters/",
    "image_url": "https://www.nasa.gov/wp-content/uploads/2026/05/crew-11-hq-visit-advisory-may-29.jpg",
    "news_site": "NASA",
    "summary": "NASA will host a public event featuring three crew members from the agency’s SpaceX Crew-11 mission at 11 a.m. EDT Monday, June 1. The event, which takes place during the crew’s standard postflight visit, will be held in the Webb Auditorium at NASA Headquarters in the Mary W. Jackson building, 300 E. Street SW in […]",
    "published_at": "2026-05-29T20:49:43Z",
    "updated_at": "2026-05-29T20:50:05.728049Z",
    "featured": false,
    "launches": [],
    "events": [],
    "detailed_news": ""
  },
  {
    "id": 38163,
    "title": "China’s Shenzhou-21 Crew Returns to Earth",
    "authors": [
      {
        "name": "Marcia Smith",
        "socials": null
      }
    ],
    "url": "https://spacepolicyonline.com/news/chinas-shenzhou-21-crew-returns-to-earth/",
    "image_url": "https://spacepolicyonline.com/wp-content/uploads/2025/10/Shenzhou-21-crew-Xinhua-300x205.png",
    "news_site": "SpacePolicyOnline.com",
    "summary": "China’s three-man Shenzhou-21 (SZ-21) crew returned to Earth today after 210 days aboard the Tiangong space station. They landed not in the SZ-21 spacecraft, however, but SZ-22. SZ-22 was launched […]",
    "published_at": "2026-05-29T17:56:42Z",
    "updated_at": "2026-05-29T18:00:22.782366Z",
    "featured": false,
    "launches": [],
    "events": [],
    "detailed_news": ""
  },
  {
    "id": 38162,
    "title": "Space Force awards SpaceX $4.16 billion to build satellite network for airborne target tracking",
    "authors": [
      {
        "name": "Sandra Erwin",
        "socials": null
      }
    ],
    "url": "https://spacenews.com/space-force-awards-spacex-4-16-billion-to-build-satellite-network-for-airborne-target-tracking/",
    "image_url": "https://i0.wp.com/spacenews.com/wp-content/uploads/2026/05/Screenshot-2026-05-29-at-12.37.49-PM.png?fit=1024%2C542&ssl=1",
    "news_site": "SpaceNews",
    "summary": "\nThe low-orbit satellite constellation is intended to track aircraft, cruise missiles and other airborne threats\nThe post Space Force awards SpaceX $4.16 billion to build satellite network for airborne target tracking appeared first on SpaceNews.",
    "published_at": "2026-05-29T16:52:57Z",
    "updated_at": "2026-05-29T17:00:26.799218Z",
    "featured": false,
    "launches": [],
    "events": [],
    "detailed_news": ""
  },
  {
    "id": 38161,
    "title": "NASA’s Roman Space Telescope Primary Mirror Gets Last Look",
    "authors": [
      {
        "name": "NASA",
        "socials": null
      }
    ],
    "url": "https://www.nasa.gov/missions/roman-space-telescope/nasas-roman-space-telescope-primary-mirror-gets-last-look/",
    "image_url": "https://www.nasa.gov/wp-content/uploads/2026/05/mirror01.jpg",
    "news_site": "NASA",
    "summary": "Engineers at NASA’s Goddard Space Flight Center in Greenbelt, Maryland, have completed their final inspection of a key element for the agency’s Nancy Grace Roman Space Telescope: the primary mirror. This 7.9-foot (2.4-meter) mirror will collect and focus light from cosmic objects near and far, helping Roman capture stunning panoramas of space. “The Roman engineering […]",
    "published_at": "2026-05-29T16:33:00Z",
    "updated_at": "2026-05-29T16:40:06.192846Z",
    "featured": false,
    "launches": [],
    "events": [],
    "detailed_news": ""
  },
  {
    "id": 38160,
    "title": "Hubble Spies Faint Irregular Galaxy",
    "authors": [
      {
        "name": "NASA",
        "socials": null
      }
    ],
    "url": "https://www.nasa.gov/image-article/hubble-spies-faint-irregular-galaxy/",
    "image_url": "https://www.nasa.gov/wp-content/uploads/2026/05/eso490-017-1-flat-final-crop.jpg",
    "news_site": "NASA",
    "summary": "This NASA Hubble Space Telescope image released on May 27, 2026, features the dwarf irregular galaxy ESO 490-017, roughly 12,000 light-years in diameter and some 23 million light-years away in the constellation Canis Major. The galaxy’s low surface brightness makes it appear as a faint, starry swarm behind brighter foreground stars that are easily recognized by their diffraction spikes. […]",
    "published_at": "2026-05-29T16:14:26Z",
    "updated_at": "2026-05-29T16:20:07.221001Z",
    "featured": false,
    "launches": [],
    "events": [],
    "detailed_news": "This NASA Hubble Space Telescope image released on May 27, 2026, features the dwarf irregular galaxy ESO 490-017, roughly 12,000 light-years in diameter and some 23 million light-years away in the constellation Canis Major. The galaxy’s low surface brightness makes it appear as a faint, starry swarm behind brighter foreground stars that are easily recognized by their diffraction spikes. […]"
  },
  {
    "id": 38159,
    "title": "This Month at ESA: May 2026",
    "authors": [
      {
        "name": "ESA",
        "socials": null
      }
    ],
    "url": "https://www.esa.int/ESA_Multimedia/Videos/2026/05/This_Month_at_ESA_May_2026",
    "image_url": "https://www.esa.int/var/esa/storage/images/esa_multimedia/videos/2026/05/this_month_at_esa_may_2026/27300539-1-eng-GB/This_Month_at_ESA_May_2026_card_full.png",
    "news_site": "ESA",
    "summary": "What did space deliver for Europe this month? From asteroid flybys to Mars landing tests, new discoveries from Webb and Hubble, and ESA astronaut Sophie Adenot capturing shooting stars from orbit, here’s your monthly roundup from the European Space Agency.",
    "published_at": "2026-05-29T15:00:00Z",
    "updated_at": "2026-05-29T15:10:20.297309Z",
    "featured": false,
    "launches": [],
    "events": [],
    "detailed_news": ""
  },
  {
    "id": 38158,
    "title": "Space Force’s commercial gatekeeper offers a playbook for startups seeking defense business",
    "authors": [
      {
        "name": "Sandra Erwin",
        "socials": null
      }
    ],
    "url": "https://spacenews.com/space-forces-commercial-gatekeeper-offers-a-playbook-for-startups-seeking-defense-business/",
    "image_url": "https://i0.wp.com/spacenews.com/wp-content/uploads/2026/05/9676735-scaled-e1780065989126.jpg?fit=1024%2C655&ssl=1",
    "news_site": "SpaceNews",
    "summary": "\nCOMSO chief Col. Tim Trimailo says transparency, patience and a clear military value proposition matter as much as technical innovation\nThe post Space Force’s commercial gatekeeper offers a playbook for startups seeking defense business appeared first on SpaceNews.",
    "published_at": "2026-05-29T14:53:49Z",
    "updated_at": "2026-05-29T15:00:32.395024Z",
    "featured": false,
    "launches": [],
    "events": [],
    "detailed_news": ""
  },
  {
    "id": 38156,
    "title": "Bellatrix and TelePIX plan 2028 air-breathing VLEO imaging demonstration",
    "authors": [
      {
        "name": "Jason Rainbow",
        "socials": {
          "x": "",
          "youtube": "",
          "instagram": "",
          "linkedin": "https://www.linkedin.com/in/jasonrainbow",
          "mastodon": "",
          "bluesky": ""
        }
      }
    ],
    "url": "https://spacenews.com/bellatrix-and-telepix-plan-2028-air-breathing-vleo-imaging-demonstration/",
    "image_url": "https://i0.wp.com/spacenews.com/wp-content/uploads/2026/05/Bellatrix-ceremony-scaled.jpg?fit=1024%2C931&ssl=1",
    "news_site": "SpaceNews",
    "summary": "\nSouth Korean optical payload developer TelePIX and Indian propulsion specialist Bellatrix Aerospace have teamed up on a very low Earth orbit geospatial demonstration mission slated for 2028.\nThe post Bellatrix and TelePIX plan 2028 air-breathing VLEO imaging demonstration appeared first on SpaceNews.",
    "published_at": "2026-05-29T13:36:35Z",
    "updated_at": "2026-05-29T13:40:33.116513Z",
    "featured": false,
    "launches": [],
    "events": [],
    "detailed_news": ""
  },
  {
    "id": 38155,
    "title": "Week in images: 25-29 May 2026",
    "authors": [
      {
        "name": "ESA",
        "socials": null
      }
    ],
    "url": "https://www.esa.int/About_Us/Week_in_images/Week_in_images_25-29_May_2026",
    "image_url": "https://www.esa.int/var/esa/storage/images/esa_multimedia/images/2026/05/journey_to_the_centre_of_a_galaxy_cluster/27296765-1-eng-GB/Journey_to_the_centre_of_a_galaxy_cluster_card_full.jpg",
    "news_site": "ESA",
    "summary": "Week in images: 25-29 May 2026",
    "published_at": "2026-05-29T13:10:00Z",
    "updated_at": "2026-05-29T13:40:19.924849Z",
    "featured": false,
    "launches": [],
    "events": [],
    "detailed_news": ""
  },
  {
    "id": 38157,
    "title": "ESA and EDF strengthen their partnership for energy efficiency at Europe’s Spaceport",
    "authors": [
      {
        "name": "ESA",
        "socials": null
      }
    ],
    "url": "https://www.esa.int/Enabling_Support/Space_Transportation/ESA_and_EDF_strengthen_their_partnership_for_energy_efficiency_at_Europe_s_Spaceport",
    "image_url": "https://www.esa.int/var/esa/storage/images/esa_multimedia/images/2026/05/signature_of_esa-edf_partnership_agreement/27300183-1-eng-GB/Signature_of_ESA-EDF_partnership_agreement_card_full.jpg",
    "news_site": "ESA",
    "summary": "From the ESA Blogs.",
    "published_at": "2026-05-29T13:05:00Z",
    "updated_at": "2026-05-29T14:20:13.470187Z",
    "featured": false,
    "launches": [],
    "events": [],
    "detailed_news": ""
  },
  {
    "id": 38153,
    "title": "Here's why the failure of Blue Origin's New Glenn rocket is so catastrophic",
    "authors": [
      {
        "name": "Eric Berger",
        "socials": null
      }
    ],
    "url": "https://arstechnica.com/space/2026/05/heres-why-the-failure-of-blue-origins-new-glenn-rocket-is-so-catastrophic/",
    "image_url": "https://cdn.arstechnica.net/wp-content/uploads/2025/11/NG-2-Ascent-11.jpg",
    "news_site": "Arstechnica",
    "summary": "\"I hope that it makes it far enough away from the pad that it does not cause pad damage.\"",
    "published_at": "2026-05-29T12:43:35Z",
    "updated_at": "2026-05-29T12:50:04.826501Z",
    "featured": false,
    "launches": [],
    "events": [],
    "detailed_news": ""
  },
  {
    "id": 38154,
    "title": "Here's why the failure of Blue Origin's New Glenn rocket is so catastrophic",
    "authors": [
      {
        "name": "Eric Berger",
        "socials": null
      }
    ],
    "url": "https://arstechnica.com/features/2026/05/heres-why-the-failure-of-blue-origins-new-glenn-rocket-is-so-catastrophic/",
    "image_url": "https://cdn.arstechnica.net/wp-content/uploads/2025/11/NG-2-Ascent-11.jpg",
    "news_site": "Arstechnica",
    "summary": "\"I hope that it makes it far enough away from the pad that it does not cause pad damage.\"",
    "published_at": "2026-05-29T12:43:35Z",
    "updated_at": "2026-05-29T13:40:08.592986Z",
    "featured": false,
    "launches": [],
    "events": [],
    "detailed_news": ""
  },
  {
    "id": 38151,
    "title": "Spatial data has become a weapon of war in the US-Iran war",
    "authors": [
      {
        "name": "Qurat-Ul-Ain Shabbir",
        "socials": null
      }
    ],
    "url": "https://spacenews.com/spatial-data-has-become-a-weapon-of-war-in-the-us-iran-war/",
    "image_url": "https://i0.wp.com/spacenews.com/wp-content/uploads/2026/02/irandust_tmo_20250122_lrg-scaled.jpg?fit=1024%2C782&ssl=1",
    "news_site": "SpaceNews",
    "summary": "\nWe are in the geospatial era of warfare in which information derived from satellites is as strategically critical as territorial control. The progressive dissolution of the distinction between the civil […]\nThe post Spatial data has become a weapon of war in the US-Iran war appeared first on SpaceNews.",
    "published_at": "2026-05-29T12:00:00Z",
    "updated_at": "2026-05-29T12:00:58.498779Z",
    "featured": false,
    "launches": [],
    "events": [],
    "detailed_news": ""
  },
  {
    "id": 38152,
    "title": "Hubble Captures M88 on Journey to Center of Virgo Cluster",
    "authors": [
      {
        "name": "NASA",
        "socials": null
      }
    ],
    "url": "https://science.nasa.gov/missions/hubble/hubble-captures-m88-on-journey-to-center-of-virgo-cluster/",
    "image_url": "https://assets.science.nasa.gov/dynamicimage/assets/science/missions/hubble/galaxies/spiral/Hubble_M88_potm2605a.jpg",
    "news_site": "NASA",
    "summary": "This NASA Hubble Space Telescope image features the active spiral galaxy Messier 88 (M88), located about 63 million light-years away.",
    "published_at": "2026-05-29T11:29:09Z",
    "updated_at": "2026-05-29T12:43:13.034752Z",
    "featured": false,
    "launches": [
      {
        "launch_id": "9d2a03ff-1fb2-4519-bcdb-ba9f84e61d3d",
        "provider": "Launch Library 2"
      }
    ],
    "events": [],
    "detailed_news": ""
  },
  {
    "id": 38150,
    "title": "China’s latest batch of new and reusable rockets are close to launch",
    "authors": [
      {
        "name": "Andrew Jones",
        "socials": null
      }
    ],
    "url": "https://spacenews.com/chinas-latest-batch-of-new-and-reusable-rockets-are-close-to-launch/",
    "image_url": "https://i0.wp.com/spacenews.com/wp-content/uploads/2026/05/Pallas1-dongfeng-commercial-launch-zone-May2026-Galactic-Energy.jpg?fit=1024%2C534&ssl=1",
    "news_site": "SpaceNews",
    "summary": "A number of new Chinese state-led and commercial rockets are set for debuts and fresh first stage recovery attempts in the coming weeks and months.\r\nThe post China’s latest batch of new and reusable rockets are close to launch appeared first on SpaceNews.",
    "published_at": "2026-05-29T09:38:40Z",
    "updated_at": "2026-05-29T11:14:12.341824Z",
    "featured": false,
    "launches": [
      {
        "launch_id": "163c666e-6c61-4e10-8110-6d3c33d965f6",
        "provider": "Launch Library 2"
      },
      {
        "launch_id": "a927b2f9-f9a5-4196-9abb-2e275e4a6b96",
        "provider": "Launch Library 2"
      },
      {
        "launch_id": "84f8dd64-8146-45e1-b34c-7df662a59c65",
        "provider": "Launch Library 2"
      },
      {
        "launch_id": "459225a2-dc1a-43d7-8c2c-78f9552b0a05",
        "provider": "Launch Library 2"
      },
      {
        "launch_id": "1e79a5e9-c02c-470f-882f-884120100fef",
        "provider": "Launch Library 2"
      }
    ],
    "events": [],
    "detailed_news": ""
  },
  {
    "id": 38148,
    "title": "Journey to the centre of a galaxy cluster",
    "authors": [
      {
        "name": "ESA",
        "socials": null
      }
    ],
    "url": "https://www.esa.int/ESA_Multimedia/Images/2026/05/Journey_to_the_centre_of_a_galaxy_cluster",
    "image_url": "https://www.esa.int/var/esa/storage/images/esa_multimedia/images/2026/05/journey_to_the_centre_of_a_galaxy_cluster/27296765-1-eng-GB/Journey_to_the_centre_of_a_galaxy_cluster_card_full.jpg",
    "news_site": "ESA",
    "summary": "From the ESA Blogs.",
    "published_at": "2026-05-29T08:00:00Z",
    "updated_at": "2026-05-29T08:22:41.407113Z",
    "featured": false,
    "launches": [
      {
        "launch_id": "9d2a03ff-1fb2-4519-bcdb-ba9f84e61d3d",
        "provider": "Launch Library 2"
      }
    ],
    "events": [],
    "detailed_news": ""
  },
  {
    "id": 38149,
    "title": "Earth from Space: Batagaika Crater",
    "authors": [
      {
        "name": "ESA",
        "socials": null
      }
    ],
    "url": "https://www.esa.int/ESA_Multimedia/Images/2026/05/Earth_from_Space_Batagaika_Crater",
    "image_url": "https://www.esa.int/var/esa/storage/images/esa_multimedia/images/2026/05/earth_from_space_batagaika_crater/27298889-1-eng-GB/Earth_from_Space_Batagaika_Crater_card_full.jpg",
    "news_site": "ESA",
    "summary": "From the ESA Blogs.",
    "published_at": "2026-05-29T08:00:00Z",
    "updated_at": "2026-05-29T09:10:17.271946Z",
    "featured": false,
    "launches": [],
    "events": [],
    "detailed_news": ""
  }
]